odoo10_addon_l10n_fr_department-10.0.1.1.0-nspkg.pth
odoo/addons/l10n_fr_department/README.rst
odoo/addons/l10n_fr_department/__init__.py
odoo/addons/l10n_fr_department/__manifest__.py
odoo/addons/l10n_fr_department/post_install.py
odoo/addons/l10n_fr_department/data/res_country_department_data.yml
odoo/addons/l10n_fr_department/i18n/am.po
odoo/addons/l10n_fr_department/i18n/bg.po
odoo/addons/l10n_fr_department/i18n/ca.po
odoo/addons/l10n_fr_department/i18n/da.po
odoo/addons/l10n_fr_department/i18n/de.po
odoo/addons/l10n_fr_department/i18n/el_GR.po
odoo/addons/l10n_fr_department/i18n/es.po
odoo/addons/l10n_fr_department/i18n/es_ES.po
odoo/addons/l10n_fr_department/i18n/es_MX.po
odoo/addons/l10n_fr_department/i18n/fi.po
odoo/addons/l10n_fr_department/i18n/fr.po
odoo/addons/l10n_fr_department/i18n/fr_CH.po
odoo/addons/l10n_fr_department/i18n/gl.po
odoo/addons/l10n_fr_department/i18n/hr.po
odoo/addons/l10n_fr_department/i18n/it.po
odoo/addons/l10n_fr_department/i18n/l10n_fr_department.pot
odoo/addons/l10n_fr_department/i18n/nb_NO.po
odoo/addons/l10n_fr_department/i18n/nl.po
odoo/addons/l10n_fr_department/i18n/pt.po
odoo/addons/l10n_fr_department/i18n/pt_BR.po
odoo/addons/l10n_fr_department/i18n/pt_PT.po
odoo/addons/l10n_fr_department/i18n/sl.po
odoo/addons/l10n_fr_department/i18n/tr.po
odoo/addons/l10n_fr_department/model/__init__.py
odoo/addons/l10n_fr_department/model/res_country_department.py
odoo/addons/l10n_fr_department/model/res_country_state.py
odoo/addons/l10n_fr_department/model/res_partner.py
odoo/addons/l10n_fr_department/security/ir.model.access.csv
odoo/addons/l10n_fr_department/static/description/icon.png
odoo/addons/l10n_fr_department/static/src/img/screenshots/department_list.jpg
odoo/addons/l10n_fr_department/tests/__init__.py
odoo/addons/l10n_fr_department/tests/test_department.py
odoo/addons/l10n_fr_department/view/res_country_department.xml
odoo/addons/l10n_fr_department/view/res_partner.xml
odoo10_addon_l10n_fr_department-10.0.1.1.0.dist-info/METADATA
odoo10_addon_l10n_fr_department-10.0.1.1.0.dist-info/WHEEL
odoo10_addon_l10n_fr_department-10.0.1.1.0.dist-info/namespace_packages.txt
odoo10_addon_l10n_fr_department-10.0.1.1.0.dist-info/top_level.txt
odoo10_addon_l10n_fr_department-10.0.1.1.0.dist-info/RECORD
